pinn/__init__.py
pinn/layers/__init__.py
pinn/layers/core.py
pinn/layers/physics.py
pinn/layers/rnn.py
pinn/layers/util.py
pml_pinn-0.0.3.dist-info/LICENSE
pml_pinn-0.0.3.dist-info/METADATA
pml_pinn-0.0.3.dist-info/WHEEL
pml_pinn-0.0.3.dist-info/top_level.txt
pml_pinn-0.0.3.dist-info/RECORD
