Metadata-Version: 2.1
Name: pml-pinn
Version: 0.0.3
Summary: Physics-informed neural networks
Home-page: https://github.com/PML-UCF/pinn
Author: Felipe A. C. Viana, Renato G. Nascimento, Yigit Yucesan, Arinan Dourado
Author-email: viana@ucf.edu, renato.gn@knights.ucf.edu, yucesan@knights.ucf.edu, arinandourado@knights.ucf.edu
License: MIT
Keywords: physics informed,neural networks,machine learning,deep learning,tensorflow,keras,python
Platform: UNKNOWN
Classifier: Development Status :: 3 - Alpha
Classifier: Intended Audience :: Education
Classifier: Intended Audience :: Science/Research
Classifier: License :: OSI Approved :: MIT License
Classifier: Operating System :: OS Independent
Classifier: Programming Language :: Python
Classifier: Programming Language :: Python :: 3.6
Classifier: Topic :: Education
Classifier: Topic :: Scientific/Engineering
Classifier: Topic :: Scientific/Engineering :: Physics
Classifier: Topic :: Scientific/Engineering :: Artificial Intelligence
Requires-Dist: numpy
Requires-Dist: tensorflow
